cli/__init__.py
cli/core.py
cli/main.py
cli/command/__init__.py
cli/command/ai.py
cli/command/img.py
cli/command/refactor.py
chatgpt_cli_tool-1.11.0.dist-info/LICENSE
chatgpt_cli_tool-1.11.0.dist-info/METADATA
chatgpt_cli_tool-1.11.0.dist-info/WHEEL
chatgpt_cli_tool-1.11.0.dist-info/entry_points.txt
chatgpt_cli_tool-1.11.0.dist-info/top_level.txt
chatgpt_cli_tool-1.11.0.dist-info/RECORD
