Metadata-Version: 2.1
Name: chatgpt-cli-tool
Version: 1.11.0
Summary: Command-line interface tool for interacting with ChatGPT using terminal
Home-page: https://github.com/lmatosevic/chatgpt-cli
Download-URL: https://github.com/lmatosevic/chatgpt-cli/archive/refs/tags/1.11.0.tar.gz
Author: luka
Author-email: lukamatosevic5@gmail.com
License: MIT
Keywords: chatgpt,openai,dall-e,cli,chat
Classifier: Development Status :: 5 - Production/Stable
Classifier: License :: OSI Approved :: MIT License
Classifier: Programming Language :: Python :: 3.8
Classifier: Programming Language :: Python :: 3.9
Classifier: Programming Language :: Python :: 3.10
Classifier: Programming Language :: Python :: 3.11
Classifier: Programming Language :: Python :: 3.12
Classifier: Programming Language :: Python :: 3.13
Requires-Python: >=3.8.0
License-File: LICENSE
Requires-Dist: openai (==1.107.0)
Requires-Dist: python-dotenv (==1.1.1)
Requires-Dist: colorama (==0.4.6)
Requires-Dist: prompt-toolkit (==3.0.52)
